adva_module/__init__.py
adva_module/adva.py
adva_module-1.2.dist-info/LICENSE
adva_module-1.2.dist-info/METADATA
adva_module-1.2.dist-info/WHEEL
adva_module-1.2.dist-info/top_level.txt
adva_module-1.2.dist-info/RECORD
