Metadata-Version: 2.1
Name: adva-module
Version: 1.2
Summary: A Python package to get REST API ADVA Information
Home-page: https://github.com/cocuni80/adva_module
Author: Jorge Riveros
Author-email: christian.riveros@outlook.com
License: MIT
Platform: UNKNOWN
Classifier: Programming Language :: Python :: 3
Classifier: License :: OSI Approved :: MIT License
Classifier: Operating System :: OS Independent
Requires-Python: >=3.x
License-File: LICENSE
Requires-Dist: requests
Requires-Dist: urllib3
